braindead/__init__.py
braindead/__main__.py
braindead/commands.py
braindead/config.py
braindead/constants.py
braindead/context.py
braindead/default_config.toml
braindead/default_template/atoms/footer.html
braindead/default_template/atoms/header.html
braindead/default_template/atoms/nav.html
braindead/default_template/detail.html
braindead/default_template/index.html
braindead/default_template/static/styles/highlighting.css
braindead/default_template/static/styles/highlighting.min.css
braindead/default_template/static/styles/style.css
braindead/default_template/static/styles/style.min.css
braindead/files.py
braindead/i18n.py
braindead/jinja_filters.py
braindead/jinja_utils.py
braindead/markdown_utils.py
braindead/rendering.py
braindead-0.3.13.dist-info/METADATA
braindead-0.3.13.dist-info/WHEEL
braindead-0.3.13.dist-info/entry_points.txt
braindead-0.3.13.dist-info/RECORD
