Metadata-Version: 2.1
Name: braindead
Version: 0.3.13
Summary: Braindead is a braindead simple static site generator for minimalists, that has support for markdown and code highlighting.
Home-page: https://grski.pl/
License: MIT
Keywords: ssg,static site generator,braindead
Author: Olaf Górski
Requires-Python: >=3.10,<4.0
Classifier: License :: OSI Approved :: MIT License
Classifier: Programming Language :: Python :: 3
Classifier: Programming Language :: Python :: 3.10
Classifier: Programming Language :: Python :: 3.11
Requires-Dist: cleo (>=0.8.1,<0.9.0)
Requires-Dist: jinja2 (==3.0.3)
Requires-Dist: markdown (>=3.4.1,<4.0.0)
Requires-Dist: pygments (>=2.6.1,<3.0.0)
Requires-Dist: toml (>=0.10.2,<0.11.0)
Project-URL: Documentation, https://github.com/grski/braindead
Project-URL: Repository, https://github.com/grski/braindead
